[
{"Producto": "Jugo Polvo Limonada Rosa Clight Sob 7.5 Grm", "Precio": 44.29, "Imagen": "https://static.cotodigital3.com.ar/sitios/fotos/medium/00532000/00532070.jpg?3.0.138b"},
{"Producto": "Jugo En Polvo Clight Naranja Dulce Vitc+D 7.5g\r\n", "Precio": 44.29, "Imagen": "https://static.cotodigital3.com.ar/sitios/fotos/medium/00511500/00511565.jpg?3.0.138b"},
{"Producto": "Jugo En Polvo CLIGHT Manzana Verde Vit C+D 7,5g", "Precio": 44.29, "Imagen": "https://static.cotodigital3.com.ar/sitios/fotos/medium/00511500/00511551.jpg?3.0.138b"},
{"Producto": "Jugos Exprimido Nara Pura Fruta Ttb 330 Ml", "Precio": 196.1, "Imagen": "https://static.cotodigital3.com.ar/sitios/fotos/medium/00495800/00495870.jpg?3.0.138b"},
{"Producto": "Jug.Pvo.Diet Anan\u00e1 Clight Sob 7 Grm", "Precio": 44.29, "Imagen": "https://static.cotodigital3.com.ar/sitios/fotos/medium/00511500/00511564.jpg?3.0.138b"},
{"Producto": "Jug.Pvo.Diet Pera Clight Sob 7 Grm", "Precio": 44.29, "Imagen": "https://static.cotodigital3.com.ar/sitios/fotos/medium/00511500/00511553.jpg?3.0.138b"},
{"Producto": "Jug.Pvo.Diet Naranja Mango Clight Sob 7 Grm", "Precio": 44.29, "Imagen": "https://static.cotodigital3.com.ar/sitios/fotos/medium/00511500/00511557.jpg?3.0.138b"},
{"Producto": "Jugo En Polvo Clight Manzana Deliciosa Vitc+D 7g\r\n", "Precio": 44.29, "Imagen": "https://static.cotodigital3.com.ar/sitios/fotos/medium/00511500/00511549.jpg?3.0.138b"},
{"Producto": "Jugo HI-C Naranja Para Diluir 1,5 Lt", "Precio": 99.0, "Imagen": "https://static.cotodigital3.com.ar/sitios/fotos/medium/00528900/00528951.jpg?3.0.138b"},
{"Producto": "Jugo Berries Mix Gergal Bot 500 Ml", "Precio": 429.0, "Imagen": "https://static.cotodigital3.com.ar/sitios/fotos/medium/00497500/00497526.jpg?3.0.138b"},
{"Producto": "Jengibre Buy And Eat Bsa 120 Grm", "Precio": 209.0, "Imagen": "https://static.cotodigital3.com.ar/sitios/fotos/medium/00526300/00526341.jpg?3.0.138b"},
{"Producto": "Jugo TUTTI Multifruta Tetrabrik 1 L", "Precio": 73.62, "Imagen": "https://static.cotodigital3.com.ar/sitios/fotos/medium/00460700/00460767.jpg?3.0.138b"},
{"Producto": "Jugo  Concentrado VIRAR\u00d3 Naranja    Bidon 5 L", "Precio": 398.0, "Imagen": "https://static.cotodigital3.com.ar/sitios/fotos/medium/00115600/00115602.jpg?3.0.138b"},
{"Producto": "Jugo Concentrado Virar\u00f3 Pomelo Bidon 5 L", "Precio": 398.0, "Imagen": "https://static.cotodigital3.com.ar/sitios/fotos/medium/00115600/00115600.jpg?3.0.138b"},
{"Producto": "Jugo HI-C Manzana 2,25 Lt", "Precio": 203.96, "Imagen": "https://static.cotodigital3.com.ar/sitios/fotos/medium/00479800/00479854.jpg?3.0.138b"},
{"Producto": "Jugo CEPITA DEL VALLE Fresh Naranja 1,5 Lt", "Precio": 136.77, "Imagen": "https://static.cotodigital3.com.ar/sitios/fotos/medium/00495500/00495551.jpg?3.0.138b"},
{"Producto": "Jugo CEPITA Del Valle Fresh Pomelo 2,25 Lt", "Precio": 218.44, "Imagen": "https://static.cotodigital3.com.ar/sitios/fotos/medium/00522500/00522555.jpg?3.0.138b"},
{"Producto": "Jugo CEPITA Del Valle Fresh Naranja 2,25 Lt", "Precio": 218.44, "Imagen": "https://static.cotodigital3.com.ar/sitios/fotos/medium/00522500/00522566.jpg?3.0.138b"},
{"Producto": "Jugo CEPITA Del Valle Fresh Manzana 2,25 Lt", "Precio": 218.44, "Imagen": "https://static.cotodigital3.com.ar/sitios/fotos/medium/00522500/00522587.jpg?3.0.138b"},
{"Producto": "Jugo En Polvo VERAO Naranja Light Sobre 10 Gr", "Precio": 10.24, "Imagen": "https://static.cotodigital3.com.ar/sitios/fotos/medium/00270700/00270776.jpg?3.0.138b"},
{"Producto": "Jugo Concentrado Virar\u00f3 Pomelo Botella 1.5 L", "Precio": 155.0, "Imagen": "https://static.cotodigital3.com.ar/sitios/fotos/medium/00098500/00098573.jpg?3.0.138b"},
{"Producto": "Jugo Concentrado Virar\u00f3 Naranja Botella 1.5 L", "Precio": 155.0, "Imagen": "https://static.cotodigital3.com.ar/sitios/fotos/medium/00098500/00098571.jpg?3.0.138b"},
{"Producto": "Jugo Manzana Dulce Tutti Ttb 1 Ltr", "Precio": 116.86, "Imagen": "https://static.cotodigital3.com.ar/sitios/fotos/medium/00533300/00533368.jpg?3.0.138b"},
{"Producto": "Jugo Mix De Frutas Tutti Ttb 1 Ltr", "Precio": 116.86, "Imagen": "https://static.cotodigital3.com.ar/sitios/fotos/medium/00533300/00533367.jpg?3.0.138b"},
{"Producto": "Jugo CEPITA Del Valle Fresh Manzana 1,5 Lt", "Precio": 183.17, "Imagen": "https://static.cotodigital3.com.ar/sitios/fotos/medium/00513600/00513675.jpg?3.0.138b"},
{"Producto": "Jugo CEPITA DEL VALLE Fresh Pomelo 1,5 Lt", "Precio": 183.17, "Imagen": "https://static.cotodigital3.com.ar/sitios/fotos/medium/00495500/00495550.jpg?3.0.138b"},
{"Producto": "Jugo Polvo Naranja Arcor Sob 18 Grm", "Precio": 24.0, "Imagen": "https://static.cotodigital3.com.ar/sitios/fotos/medium/00511800/00511828.jpg?3.0.138b"},
{"Producto": "Jugo Polvo Manzana Arcor Sob 18 Grm", "Precio": 24.45, "Imagen": "https://static.cotodigital3.com.ar/sitios/fotos/medium/00511800/00511823.jpg?3.0.138b"},
{"Producto": "Jugo Durazno TUTTI Ttb 1 Ltr", "Precio": 138.5, "Imagen": "https://static.cotodigital3.com.ar/sitios/fotos/medium/00484600/00484651.jpg?3.0.138b"},
{"Producto": "Jugo   TUTTI Naranja    Tetrabrik 1 L", "Precio": 139.8, "Imagen": "https://static.cotodigital3.com.ar/sitios/fotos/medium/00460700/00460770.jpg?3.0.138b"},
{"Producto": "Jugo Natural C/Pulpa Manzan Petit Ttb 1 Ltr", "Precio": 144.8, "Imagen": "https://static.cotodigital3.com.ar/sitios/fotos/medium/00492200/00492261.jpg?3.0.138b"},
{"Producto": "Jugo Natural C/Pulpa Naranja PETIT Ttb 1 Ltr", "Precio": 144.8, "Imagen": "https://static.cotodigital3.com.ar/sitios/fotos/medium/00490100/00490174.jpg?3.0.138b"},
{"Producto": "Jugo Polvo Naranja/Banana Arcor Sob 18 Grm", "Precio": 30.95, "Imagen": "https://static.cotodigital3.com.ar/sitios/fotos/medium/00511800/00511826.jpg?3.0.138b"},
{"Producto": "Jugo Polvo Durazno Arcor Sob 18 Grm", "Precio": 30.95, "Imagen": "https://static.cotodigital3.com.ar/sitios/fotos/medium/00511800/00511819.jpg?3.0.138b"},
{"Producto": "Jugo Polvo Naranja Dulce Arcor Sob 18 Grm", "Precio": 30.95, "Imagen": "https://static.cotodigital3.com.ar/sitios/fotos/medium/00511800/00511829.jpg?3.0.138b"},
{"Producto": "Jugo Polvo Multifruta Arcor Sob 18 Grm", "Precio": 30.95, "Imagen": "https://static.cotodigital3.com.ar/sitios/fotos/medium/00511800/00511822.jpg?3.0.138b"},
{"Producto": "Jugo Polvo Naranja/Mango Arcor Sob 18 Grm", "Precio": 30.95, "Imagen": "https://static.cotodigital3.com.ar/sitios/fotos/medium/00511800/00511824.jpg?3.0.138b"},
{"Producto": "Jugo Polvo Limonada Arcor Sob 18 Grm", "Precio": 30.95, "Imagen": "https://static.cotodigital3.com.ar/sitios/fotos/medium/00511800/00511827.jpg?3.0.138b"},
{"Producto": "Jugo Polvo Naranja/Durazn Arcor Sob 18 Grm", "Precio": 30.95, "Imagen": "https://static.cotodigital3.com.ar/sitios/fotos/medium/00511800/00511821.jpg?3.0.138b"},
{"Producto": "Jugo Polvo Frutilla Arcor Sob 18 Grm", "Precio": 30.95, "Imagen": "https://static.cotodigital3.com.ar/sitios/fotos/medium/00511800/00511825.jpg?3.0.138b"},
{"Producto": "Jugo Polvo Anan\u00e1 Arcor Sob 18 Grm", "Precio": 30.95, "Imagen": "https://static.cotodigital3.com.ar/sitios/fotos/medium/00511800/00511820.jpg?3.0.138b"},
{"Producto": "Jugo Limonada Del Valle Ttb 1 Ltr", "Precio": 172.0, "Imagen": "https://static.cotodigital3.com.ar/sitios/fotos/medium/00529700/00529771.jpg?3.0.138b"},
{"Producto": "Jugo Naranja Del Valle Ttb 1 Ltr", "Precio": 185.0, "Imagen": "https://static.cotodigital3.com.ar/sitios/fotos/medium/00531500/00531525.jpg?3.0.138b"},
{"Producto": "Jugo Manzana Del Valle Ttb 1 Ltr", "Precio": 185.0, "Imagen": "https://static.cotodigital3.com.ar/sitios/fotos/medium/00529700/00529773.jpg?3.0.138b"},
{"Producto": "Jugo Multifruta Del Valle Ttb 1 Ltr", "Precio": 185.0, "Imagen": "https://static.cotodigital3.com.ar/sitios/fotos/medium/00531500/00531526.jpg?3.0.138b"},
{"Producto": "Jugo Polvo 3 Frutas Arcor Sob 18 Grm", "Precio": 33.49, "Imagen": "https://static.cotodigital3.com.ar/sitios/fotos/medium/00528900/00528959.jpg?3.0.138b"},
{"Producto": "Jugo CEPITA DEL VALLE Multifruta 1 Lt", "Precio": 190.24, "Imagen": "https://static.cotodigital3.com.ar/sitios/fotos/medium/00503100/00503180.jpg?3.0.138b"},
{"Producto": "Jugo CEPITA DEL VALLE Manzana 1 Lt", "Precio": 190.24, "Imagen": "https://static.cotodigital3.com.ar/sitios/fotos/medium/00503100/00503179.jpg?3.0.138b"},
{"Producto": "Jugo CEPITA DEL VALLE Naranja Tentaci\u00f3n 1 Lt", "Precio": 190.24, "Imagen": "https://static.cotodigital3.com.ar/sitios/fotos/medium/00297900/00297931.jpg?3.0.138b"},
{"Producto": "Jugo CEPITA Del Valle 20% Naranja Tentaci\u00f3n 1 Lt", "Precio": 190.24, "Imagen": "https://static.cotodigital3.com.ar/sitios/fotos/medium/00534100/00534114.jpg?3.0.138b"},
{"Producto": "Jugo CEPITA DEL VALLE Durazno Delicioso 1 Lt", "Precio": 190.24, "Imagen": "https://static.cotodigital3.com.ar/sitios/fotos/medium/00297900/00297928.jpg?3.0.138b"},
{"Producto": "Jugo CEPITA DEL VALLE Fresh Naranja 500 Ml", "Precio": 95.5, "Imagen": "https://static.cotodigital3.com.ar/sitios/fotos/medium/00511100/00511153.jpg?3.0.138b"},
{"Producto": "Jugo En Polvo TANG Durazno Vitamina C+D 18g", "Precio": 34.73, "Imagen": "https://static.cotodigital3.com.ar/sitios/fotos/medium/00511700/00511717.jpg?3.0.138b"},
{"Producto": "Jugo En Polvo TANG Mix Naranja Lima Vitc+D 18g", "Precio": 34.8, "Imagen": "https://static.cotodigital3.com.ar/sitios/fotos/medium/00511800/00511844.jpg?3.0.138b"},
{"Producto": "Jugo Naranja Valencia Tutti Ttb 200 Ml", "Precio": 40.03, "Imagen": "https://static.cotodigital3.com.ar/sitios/fotos/medium/00533300/00533370.jpg?3.0.138b"},
{"Producto": "Jugo Manzana Dulce Tutti Ttb 200 Ml", "Precio": 40.03, "Imagen": "https://static.cotodigital3.com.ar/sitios/fotos/medium/00533300/00533355.jpg?3.0.138b"},
{"Producto": "Jugo Durazno De La Huerta Tutti Ttb 200 Ml", "Precio": 40.03, "Imagen": "https://static.cotodigital3.com.ar/sitios/fotos/medium/00533300/00533356.jpg?3.0.138b"},
{"Producto": "Jugo Mix De Frutas Tutti Ttb 200 Ml", "Precio": 40.03, "Imagen": "https://static.cotodigital3.com.ar/sitios/fotos/medium/00533300/00533369.jpg?3.0.138b"},
{"Producto": "Jugo CEPITA DEL VALLE Multifruta 200 Ml", "Precio": 74.12, "Imagen": "https://static.cotodigital3.com.ar/sitios/fotos/medium/00207600/00207652.jpg?3.0.138b"},
{"Producto": "Jugo CEPITA DEL VALLE Manzana 200 Ml", "Precio": 74.12, "Imagen": "https://static.cotodigital3.com.ar/sitios/fotos/medium/00207600/00207650.jpg?3.0.138b"},
{"Producto": "Jugo CEPITA DEL VALLE Naranja 200 Ml", "Precio": 74.12, "Imagen": "https://static.cotodigital3.com.ar/sitios/fotos/medium/00207600/00207649.jpg?3.0.138b"},
{"Producto": "Jugo Con Pulpa Naranja Salustiana Citric 1.5 Ltr", "Precio": 559.0, "Imagen": "https://static.cotodigital3.com.ar/sitios/fotos/medium/00539100/00539118.jpg?3.0.138b"},
{"Producto": "ADES Soja + Jugo De Naranja 1 Lt", "Precio": 200.62, "Imagen": "https://static.cotodigital3.com.ar/sitios/fotos/medium/00256100/00256105.jpg?3.0.138b"},
{"Producto": "Jugo Con Pulpa Naranja Salustiana Citric 1 Ltr", "Precio": 380.0, "Imagen": "https://static.cotodigital3.com.ar/sitios/fotos/medium/00539100/00539119.jpg?3.0.138b"},
{"Producto": "Jugo De Naranja/Durazno Citric Ttb 1 Ltr", "Precio": 380.35, "Imagen": "https://static.cotodigital3.com.ar/sitios/fotos/medium/00528900/00528908.jpg?3.0.138b"},
{"Producto": "Jugo De Manzana Citric Ttb 1 Ltr", "Precio": 380.35, "Imagen": "https://static.cotodigital3.com.ar/sitios/fotos/medium/00528900/00528910.jpg?3.0.138b"},
{"Producto": "ADES Soja + Jugo De Frutas Tropicales 1 Lt", "Precio": 200.63, "Imagen": "https://static.cotodigital3.com.ar/sitios/fotos/medium/00256200/00256245.jpg?3.0.138b"},
{"Producto": "ADES Soja + Jugo De Manzana 1 Lt", "Precio": 200.63, "Imagen": "https://static.cotodigital3.com.ar/sitios/fotos/medium/00256100/00256111.jpg?3.0.138b"},
{"Producto": "Jugo CEPITA DEL VALLE Fresh Pomelo 500 Ml", "Precio": 103.07, "Imagen": "https://static.cotodigital3.com.ar/sitios/fotos/medium/00511100/00511154.jpg?3.0.138b"},
{"Producto": "Jugo De Pomelo C/Pulpa Citric Ttb 1 Ltr", "Precio": 380.35, "Imagen": "https://static.cotodigital3.com.ar/sitios/fotos/medium/00528900/00528912.jpg?3.0.138b"},
{"Producto": "Jugo De Naranja/Frutilla Citric Ttb 1 Ltr", "Precio": 380.35, "Imagen": "https://static.cotodigital3.com.ar/sitios/fotos/medium/00528900/00528911.jpg?3.0.138b"},
{"Producto": "Jugo De Naranja/Mango Citric Ttb 1 Ltr", "Precio": 380.35, "Imagen": "https://static.cotodigital3.com.ar/sitios/fotos/medium/00528900/00528909.jpg?3.0.138b"},
{"Producto": "Jugo CEPITA DEL VALLE Nutridefensas Durazno 200 Ml", "Precio": 41.71, "Imagen": "https://static.cotodigital3.com.ar/sitios/fotos/medium/00216300/00216341.jpg?3.0.138b"},
{"Producto": "Jugo En Polvo FRUTTA-MI Naranja Light Sobre 10 Gr", "Precio": 21.0, "Imagen": "https://static.cotodigital3.com.ar/sitios/fotos/medium/00478300/00478318.jpg?3.0.138b"},
{"Producto": "Jugo Light Naranja Bc Ttb 1000 Cmq", "Precio": 232.32, "Imagen": "https://static.cotodigital3.com.ar/sitios/fotos/medium/00186200/00186250.jpg?3.0.138b"},
{"Producto": "Jugo En Polvo CLIGHT Stevia Naranja Vit C+D 9,5g", "Precio": 37.26, "Imagen": "https://static.cotodigital3.com.ar/sitios/fotos/medium/00511700/00511771.jpg?3.0.138b"},
{"Producto": "Jugo Organico Manzana Pura Frutta Ttb 1 Ltr", "Precio": 395.9, "Imagen": "https://static.cotodigital3.com.ar/sitios/fotos/medium/00493000/00493090.jpg?3.0.138b"},
{"Producto": "Jugos Mezcla Ar\u00e1ndan PURA FRUTA Ttb 1 Ltr", "Precio": 401.52, "Imagen": "https://static.cotodigital3.com.ar/sitios/fotos/medium/00483400/00483402.jpg?3.0.138b"},
{"Producto": "Jugo Light Manzana Bc Ttb 1000 Cmq", "Precio": 232.32, "Imagen": "https://static.cotodigital3.com.ar/sitios/fotos/medium/00186200/00186251.jpg?3.0.138b"},
{"Producto": "Jugo Polvo Lim\u00f3n Dulce Tang Sob 18 Grm", "Precio": 41.9, "Imagen": "https://static.cotodigital3.com.ar/sitios/fotos/medium/00511700/00511719.jpg?3.0.138b"},
{"Producto": "Jugo En Polvo TANG Anana Vitc+D 18g", "Precio": 41.9, "Imagen": "https://static.cotodigital3.com.ar/sitios/fotos/medium/00511500/00511578.jpg?3.0.138b"},
{"Producto": "Jugos Exprimido Manz Pura Fruta Ttb 1 Ltr", "Precio": 401.63, "Imagen": "https://static.cotodigital3.com.ar/sitios/fotos/medium/00495800/00495872.jpg?3.0.138b"},
{"Producto": "Jugos Naranja Citric Ttb 250 Cmq", "Precio": 103.4, "Imagen": "https://static.cotodigital3.com.ar/sitios/fotos/medium/00239000/00239028.jpg?3.0.138b"},
{"Producto": "Jugos Naranja/Durazn Citric Ttb 500 Ml", "Precio": 207.95, "Imagen": "https://static.cotodigital3.com.ar/sitios/fotos/medium/00529600/00529641.jpg?3.0.138b"},
{"Producto": "Jugos Pomelo C/Pulpa Citric Ttb 500 Ml", "Precio": 207.95, "Imagen": "https://static.cotodigital3.com.ar/sitios/fotos/medium/00529600/00529644.jpg?3.0.138b"},
{"Producto": "Jugo En Polvo TANG Naranja Vitc+D 18g", "Precio": 41.9, "Imagen": "https://static.cotodigital3.com.ar/sitios/fotos/medium/00511500/00511579.jpg?3.0.138b"},
{"Producto": "TANG Frutilla Vitaminas C+D 18grm", "Precio": 41.9, "Imagen": "https://static.cotodigital3.com.ar/sitios/fotos/medium/00531900/00531996.jpg?3.0.138b"},
{"Producto": "Jugo En Polvo TANG Naranja Dulce Vitc+D 18g", "Precio": 41.9, "Imagen": "https://static.cotodigital3.com.ar/sitios/fotos/medium/00511800/00511838.jpg?3.0.138b"},
{"Producto": "Jugo Polvo Multifruta Tang Sob 18 Grm", "Precio": 41.9, "Imagen": "https://static.cotodigital3.com.ar/sitios/fotos/medium/00511800/00511842.jpg?3.0.138b"},
{"Producto": "Jugos Naranja/Frutil Citric Ttb 500 Ml", "Precio": 207.95, "Imagen": "https://static.cotodigital3.com.ar/sitios/fotos/medium/00529600/00529640.jpg?3.0.138b"},
{"Producto": "Jugos Naranja/Mango Citric Ttb 500 Ml", "Precio": 207.95, "Imagen": "https://static.cotodigital3.com.ar/sitios/fotos/medium/00529600/00529642.jpg?3.0.138b"},
{"Producto": "ADES Soja + Jugo De Manzana 200 Ml", "Precio": 85.05, "Imagen": "https://static.cotodigital3.com.ar/sitios/fotos/medium/00256100/00256107.jpg?3.0.138b"},
{"Producto": "ADES Soja + Jugo De Naranja 200 Ml", "Precio": 85.05, "Imagen": "https://static.cotodigital3.com.ar/sitios/fotos/medium/00256100/00256106.jpg?3.0.138b"},
{"Producto": "Jugo En Polvo TANG Pera Vitc+D 18g", "Precio": 41.9, "Imagen": "https://static.cotodigital3.com.ar/sitios/fotos/medium/00511500/00511581.jpg?3.0.138b"},
{"Producto": "Jugo En Polvo TANG Mix Naranja Frutilla Maracuya Vc+D 18g", "Precio": 41.9, "Imagen": "https://static.cotodigital3.com.ar/sitios/fotos/medium/00511800/00511845.jpg?3.0.138b"},
{"Producto": "Jugo Polvo Naranja Mango Tang Sob 18 Grm", "Precio": 41.9, "Imagen": "https://static.cotodigital3.com.ar/sitios/fotos/medium/00511800/00511843.jpg?3.0.138b"},
{"Producto": "Jugo Polvo Pomelo Rosado Tang Sob 18 Grm", "Precio": 41.9, "Imagen": "https://static.cotodigital3.com.ar/sitios/fotos/medium/00511800/00511839.jpg?3.0.138b"},
{"Producto": "ADES Soja + Jugo De Frutas Tropicales 200 Ml", "Precio": 85.05, "Imagen": "https://static.cotodigital3.com.ar/sitios/fotos/medium/00256100/00256108.jpg?3.0.138b"},
{"Producto": "Jugos Blend Detox Pura Frutta Ttb 1 Ltr", "Precio": 444.99, "Imagen": "https://static.cotodigital3.com.ar/sitios/fotos/medium/00528900/00528913.jpg?3.0.138b"},
{"Producto": "Jugo En Polvo Sabor Naranja Bc Sob 7 Grm", "Precio": 32.6, "Imagen": "https://static.cotodigital3.com.ar/sitios/fotos/medium/00521300/00521338.jpg?3.0.138b"},
{"Producto": "Jugo En Polvo Sabor Frutilla Lim\u00f3n Bc Sob 7 Grm", "Precio": 32.6, "Imagen": "https://static.cotodigital3.com.ar/sitios/fotos/medium/00521300/00521347.jpg?3.0.138b"},
{"Producto": "Jugo En Polvo Sabor Pomelo Amarillo Bc Sob 7 Grm", "Precio": 32.64, "Imagen": "https://static.cotodigital3.com.ar/sitios/fotos/medium/00521300/00521342.jpg?3.0.138b"},
{"Producto": "Jugo En Polvo TANG Naranja Banana Vitc+D 18g", "Precio": 41.9, "Imagen": "https://static.cotodigital3.com.ar/sitios/fotos/medium/00511800/00511840.jpg?3.0.138b"},
{"Producto": "Jugo En Polvo TANG Uva Vitc+D 18g", "Precio": 41.9, "Imagen": "https://static.cotodigital3.com.ar/sitios/fotos/medium/00511800/00511841.jpg?3.0.138b"},
{"Producto": "Jugo Polvo Naranja Durazn Tang Sob 18 Grm", "Precio": 41.9, "Imagen": "https://static.cotodigital3.com.ar/sitios/fotos/medium/00511500/00511580.jpg?3.0.138b"},
{"Producto": "Jugo En Polvo TANG Manzana Vitc+D 18g", "Precio": 41.9, "Imagen": "https://static.cotodigital3.com.ar/sitios/fotos/medium/00511500/00511577.jpg?3.0.138b"},
{"Producto": "Jugo Multifruta Del Valle Ttb 200 Ml", "Precio": 51.6, "Imagen": "https://static.cotodigital3.com.ar/sitios/fotos/medium/00529700/00529770.jpg?3.0.138b"},
{"Producto": "Jugo Polvo Sabor Mix Frutal Bc Sob 7 Grm", "Precio": 32.64, "Imagen": "https://static.cotodigital3.com.ar/sitios/fotos/medium/00524200/00524246.jpg?3.0.138b"},
{"Producto": "Jugo En Polvo CLIGHT Stevia Manzana Vit C+D 7,5g", "Precio": 36.83, "Imagen": "https://static.cotodigital3.com.ar/sitios/fotos/medium/00511700/00511773.jpg?3.0.138b"},
{"Producto": "Jugo Ar\u00e1ndanos Diet Gergal Bot 500 Ml", "Precio": 249.0, "Imagen": "https://static.cotodigital3.com.ar/sitios/fotos/medium/00526300/00526337.jpg?3.0.138b"},
{"Producto": "Jugo Mix De Berries Gergal Bot 500 Ml", "Precio": 249.0, "Imagen": "https://static.cotodigital3.com.ar/sitios/fotos/medium/00526300/00526340.jpg?3.0.138b"},
{"Producto": "Jugo Frutilla Y Frambuesa Gergal Bot 500 Ml", "Precio": 249.0, "Imagen": "https://static.cotodigital3.com.ar/sitios/fotos/medium/00526300/00526339.jpg?3.0.138b"},
{"Producto": "Jugo Maracuy\u00e1 Gergal Bot 500 Ml", "Precio": 249.0, "Imagen": "https://static.cotodigital3.com.ar/sitios/fotos/medium/00526300/00526338.jpg?3.0.138b"},
{"Producto": "Jugo Durazno Del Valle Ttb 200 Ml", "Precio": 51.6, "Imagen": "https://static.cotodigital3.com.ar/sitios/fotos/medium/00529700/00529778.jpg?3.0.138b"},
{"Producto": "Jugo Manzana Verde Del Valle Ttb 200 Ml", "Precio": 51.6, "Imagen": "https://static.cotodigital3.com.ar/sitios/fotos/medium/00529700/00529776.jpg?3.0.138b"},
{"Producto": "Jugo Naranja Del Valle Ttb 200 Ml", "Precio": 51.6, "Imagen": "https://static.cotodigital3.com.ar/sitios/fotos/medium/00529700/00529777.jpg?3.0.138b"},
{"Producto": "Jugo Manzana Del Valle Ttb 200 Ml", "Precio": 51.6, "Imagen": "https://static.cotodigital3.com.ar/sitios/fotos/medium/00529700/00529775.jpg?3.0.138b"},
{"Producto": "Jugo En Polvo FRUTTA-MI Mango Light   Sobre 8 Gr", "Precio": 21.0, "Imagen": "https://static.cotodigital3.com.ar/sitios/fotos/medium/00478300/00478315.jpg?3.0.138b"},
{"Producto": "Jugo Polvo Sabor Manzana Roja Bc Sob 7 Grm", "Precio": 34.9, "Imagen": "https://static.cotodigital3.com.ar/sitios/fotos/medium/00521300/00521341.jpg?3.0.138b"},
{"Producto": "Jugo En Polvo Sabor Naranja Durazno Bc Sob 7 Grm", "Precio": 34.9, "Imagen": "https://static.cotodigital3.com.ar/sitios/fotos/medium/00521300/00521339.jpg?3.0.138b"},
{"Producto": "Jugo En Polvo Sabor Pomelo Rosado Bc Sob 7 Grm", "Precio": 34.9, "Imagen": "https://static.cotodigital3.com.ar/sitios/fotos/medium/00521300/00521348.jpg?3.0.138b"},
{"Producto": "Jugo En Polvo Sabor Mango Naranja Bc Sob 7 Grm", "Precio": 34.9, "Imagen": "https://static.cotodigital3.com.ar/sitios/fotos/medium/00521300/00521349.jpg?3.0.138b"},
{"Producto": "Jugo En Polvo Sabor Anan\u00e1 Bc Sob 7 Grm", "Precio": 34.9, "Imagen": "https://static.cotodigital3.com.ar/sitios/fotos/medium/00521300/00521324.jpg?3.0.138b"},
{"Producto": "Jugo En Polvo Sabor Naranja Dulce Bc Sob 7 Grm", "Precio": 34.9, "Imagen": "https://static.cotodigital3.com.ar/sitios/fotos/medium/00521300/00521323.jpg?3.0.138b"},
{"Producto": "Jugo En Polvo Sabor Limonada Bc Sob 7 Grm", "Precio": 34.9, "Imagen": "https://static.cotodigital3.com.ar/sitios/fotos/medium/00521300/00521340.jpg?3.0.138b"},
{"Producto": "Jugo PURA FRUTA Manzana Roja Ttb 200 CC", "Precio": 105.63, "Imagen": "https://static.cotodigital3.com.ar/sitios/fotos/medium/00476000/00476021.jpg?3.0.138b"},
{"Producto": "Jugo PURA FRUTA Manzana Verde Ttb 200 CC", "Precio": 105.63, "Imagen": "https://static.cotodigital3.com.ar/sitios/fotos/medium/00476000/00476020.jpg?3.0.138b"},
{"Producto": "Jugo En Polvo FRUTTA-MI Maracuy\u00e1 Light   Sobre 8 Gr", "Precio": 21.0, "Imagen": "https://static.cotodigital3.com.ar/sitios/fotos/medium/00478300/00478314.jpg?3.0.138b"},
{"Producto": "Jugo FRESCOR Naranja Light Con Pulpa Botella 1 L", "Precio": 292.0, "Imagen": "https://static.cotodigital3.com.ar/sitios/fotos/medium/00183900/00183913.jpg?3.0.138b"},
{"Producto": "Jugo Frescor Naranja Azucarado Botella 1 L", "Precio": 292.0, "Imagen": "https://static.cotodigital3.com.ar/sitios/fotos/medium/00073700/00073742.jpg?3.0.138b"},
{"Producto": "Jugo   FRESCOR Pomelo    Botella 1 L", "Precio": 315.0, "Imagen": "https://static.cotodigital3.com.ar/sitios/fotos/medium/00073700/00073745.jpg?3.0.138b"},
{"Producto": "Jugo FRESCOR Pomelo Light Botella 1 L", "Precio": 315.0, "Imagen": "https://static.cotodigital3.com.ar/sitios/fotos/medium/00187500/00187520.jpg?3.0.138b"},
{"Producto": "Jugo Manzana Arcor Ttb 200 Ml", "Precio": 64.6, "Imagen": "https://static.cotodigital3.com.ar/sitios/fotos/medium/00489900/00489933.jpg?3.0.138b"},
{"Producto": "Jugo Naranja Arcor Ttb 200 Ml", "Precio": 64.6, "Imagen": "https://static.cotodigital3.com.ar/sitios/fotos/medium/00489900/00489934.jpg?3.0.138b"},
{"Producto": "Jugo En Polvo CLIGHT Pomelo Amarillo Vit C+D 8g", "Precio": 44.29, "Imagen": "https://static.cotodigital3.com.ar/sitios/fotos/medium/00511500/00511550.jpg?3.0.138b"},
{"Producto": "Jug.Pvo.Diet Naranja Clight Sob 8 Grm", "Precio": 44.29, "Imagen": "https://static.cotodigital3.com.ar/sitios/fotos/medium/00511500/00511561.jpg?3.0.138b"},
{"Producto": "Jug.Pvo.Diet Mandarina Clight Sob 8 Grm", "Precio": 44.29, "Imagen": "https://static.cotodigital3.com.ar/sitios/fotos/medium/00511700/00511778.jpg?3.0.138b"},
{"Producto": "Jug.Pvo.Diet Pomelo Rosado Clight Sob 8 Grm", "Precio": 44.29, "Imagen": "https://static.cotodigital3.com.ar/sitios/fotos/medium/00511500/00511560.jpg?3.0.138b"},
{"Producto": "Jug.Pvo.Diet Limonada Clight Sob 8 Grm", "Precio": 44.29, "Imagen": "https://static.cotodigital3.com.ar/sitios/fotos/medium/00511700/00511708.jpg?3.0.138b"},
{"Producto": "Jugos Manzana Roja Pura Fruta Ttb 330 Ml", "Precio": 190.5, "Imagen": "https://static.cotodigital3.com.ar/sitios/fotos/medium/00495800/00495873.jpg?3.0.138b"},
{"Producto": "Jugo En Polvo CLIGHT Naranja Durazno Vit C+D 7,5g", "Precio": 44.29, "Imagen": "https://static.cotodigital3.com.ar/sitios/fotos/medium/00511500/00511559.jpg?3.0.138b"},
{"Producto": "Jugo Light Manzana Bc Ttb 500 Cmq", "Precio": 162.62, "Imagen": "https://static.cotodigital3.com.ar/sitios/fotos/medium/00468400/00468439.jpg?3.0.138b"},
{"Producto": "Jugo Light Naranja Bc Ttb 500 Cmq", "Precio": 162.62, "Imagen": "https://static.cotodigital3.com.ar/sitios/fotos/medium/00468400/00468437.jpg?3.0.138b"},
{"Producto": "Jugo Light Multifruta Bc Ttb 500 Cmq", "Precio": 162.62, "Imagen": "https://static.cotodigital3.com.ar/sitios/fotos/medium/00468400/00468438.jpg?3.0.138b"},
{"Producto": "Jugo C/Pulpa Naranja Cl\u00e1sic Citric Bid 3 Ltr", "Precio": 977.95, "Imagen": "https://static.cotodigital3.com.ar/sitios/fotos/medium/00522500/00522541.jpg?3.0.138b"},
{"Producto": "Jugo De Naranja C/Pulpa Citric Ttb 750 Ml", "Precio": 246.25, "Imagen": "https://static.cotodigital3.com.ar/sitios/fotos/medium/00529600/00529646.jpg?3.0.138b"},
{"Producto": "Jugo C/Pulpa Naranja Cl\u00e1sico Citric Ttb 1.5 Ltr", "Precio": 508.1, "Imagen": "https://static.cotodigital3.com.ar/sitios/fotos/medium/00522500/00522537.jpg?3.0.138b"},
{"Producto": "Jugo PURA FRUTA Manzana Roja Ttb 1 L", "Precio": 342.62, "Imagen": "https://static.cotodigital3.com.ar/sitios/fotos/medium/00476000/00476018.jpg?3.0.138b"},
{"Producto": "Jugo PURA FRUTA Manzana Verde Ttb 1 L", "Precio": 342.62, "Imagen": "https://static.cotodigital3.com.ar/sitios/fotos/medium/00476000/00476019.jpg?3.0.138b"},
{"Producto": "Jugo De Naranja S/Pulpa Citric Ttb 1 Ltr", "Precio": 344.65, "Imagen": "https://static.cotodigital3.com.ar/sitios/fotos/medium/00529600/00529645.jpg?3.0.138b"},
{"Producto": "Jugo C/Pulpa Naranja Cl\u00e1sico Citric Ttb 1 Ltr", "Precio": 344.65, "Imagen": "https://static.cotodigital3.com.ar/sitios/fotos/medium/00522500/00522536.jpg?3.0.138b"},
{"Producto": "Jugos Expremido Naranja Pura Frutta Ttb 1 Ltr", "Precio": 353.75, "Imagen": "https://static.cotodigital3.com.ar/sitios/fotos/medium/00493000/00493089.jpg?3.0.138b"},
{"Producto": "Jugo C/Pulpa Naranja, Valen Citric Ttb 1 Ltr", "Precio": 359.9, "Imagen": "https://static.cotodigital3.com.ar/sitios/fotos/medium/00503600/00503624.jpg?3.0.138b"},
{"Producto": "Jugo CITRIC Naranja Con Pulpa Ttb 500 CC", "Precio": 185.25, "Imagen": "https://static.cotodigital3.com.ar/sitios/fotos/medium/00135200/00135293.jpg?3.0.138b"}
]